README.md
setup.cfg
setup.py
./src/MIQA.py
./src/__init__.py
./src/decision.py
./src/exception.py
./src/experiment.py
./src/frame.py
./src/project.py
./src/scan.py
miqa_python_client.egg-info/PKG-INFO
miqa_python_client.egg-info/SOURCES.txt
miqa_python_client.egg-info/dependency_links.txt
miqa_python_client.egg-info/requires.txt
miqa_python_client.egg-info/top_level.txt
src/MIQA.py
src/__init__.py
src/decision.py
src/exception.py
src/experiment.py
src/frame.py
src/project.py
src/scan.py